{
  "version": 2,
  "defaultTableId": "starter-field",
  "tables": [
    {
      "id": "starter-field",
      "mapKeys": ["town"],
      "encounterRate": 0.15,
      "speciesRanges": [{ "startNationalDexId": 1, "endNationalDexId": 493 }]
    },
    {
      "id": "town-west-field",
      "mapKeys": ["town"],
      "areaIds": ["town-west-field"],
      "encounterRate": 0.15,
      "speciesRanges": [{ "startNationalDexId": 1, "endNationalDexId": 151 }]
    },
    {
      "id": "town-plaza-field",
      "mapKeys": ["town"],
      "areaIds": ["town-plaza-field"],
      "encounterRate": 0.15,
      "speciesRanges": [{ "startNationalDexId": 152, "endNationalDexId": 251 }]
    },
    {
      "id": "town-south-field",
      "mapKeys": ["town"],
      "areaIds": ["town-south-field"],
      "encounterRate": 0.15,
      "speciesRanges": [{ "startNationalDexId": 252, "endNationalDexId": 493 }]
    }
  ]
}
